{
    "1P-16:9": {
        "position": {
            "x": 213,
            "y": 0
        },
        "scale": {
            "x": 1067,
            "y": 600
        }
    },
    "1P-10:9": {
        "position": {
            "x": 480,
            "y": 0
        },
        "scale": {
            "x": 800,
            "y": 720
        }
    },
    "1P-8:7": {
        "position": {
            "x": 457,
            "y": 0
        },
        "scale": {
            "x": 823,
            "y": 720
        }
    },
    "1P-4:3": {
        "position": {
            "x": 320,
            "y": 0
        },
        "scale": {
            "x": 960,
            "y": 720
        }
    },
    "1P-3:2": {
        "position": {
            "x": 380,
            "y": 0
        },
        "scale": {
            "x": 900,
            "y": 600
        }
    },
    "2P-8:7": [
        {
            "position": {
                "x": 0,
                "y": 0
            },
            "scale": {
                "x": 555,
                "y": 486
            }
        },
        {
            "position": {
                "x": 725,
                "y": 0
            },
            "scale": {
                "x": 555,
                "y": 486
            }
        }
    ]
}