{
    "ebloodycandy": "he/him",
    "MissedAWP": "she/they",
    "slashinfty": "he/him",
    "davesies": "he/him",
    "Ravlin": "he/him",
    "Gambit017": "he/him",
    "curtsnewbrand": "he/him",
    "moelleuh": "he/him",
    "young_xorn": "she/her",
    "antiaaron": "",
    "Mvdvegt": "he/him",
    "TempestMask1000": "",
    "thebagler5": "he/him",
    "talcerase": "he/him",
    "chocolatecake5000": "he/him",
    "briarwoodsz": "he/him",
    "ceaselessly": "they/them",
    "LudwigVonKoopa": "he/him",
    "nullsprite": "he/him",
    "sparkymccalc1": "he/him",
    "heponwana": "he/him",
    "flamesolsen": "he/him",
    "Tsira": "they/them",
    "SonicRPika": "they/her",
    "tpasalt": "he/him",
    "theboyks": "he/him",
    "Ozmourn": "he/him",
    "Ryan_Ford": "",
    "iceplug": "he/him",
    "ThefakeDabilicious2121": "he/him",
    "knockels": "he/him"
}